setup.py
stathat.py
python_stathat.egg-info/PKG-INFO
python_stathat.egg-info/SOURCES.txt
python_stathat.egg-info/dependency_links.txt
python_stathat.egg-info/requires.txt
python_stathat.egg-info/top_level.txt
python_stathat.egg-info/zip-safe