Metadata-Version: 1.0
Name: python-stathat
Version: 0.2.0
Summary: A better Python library for StatHat
Home-page: https://github.com/mattrobenolt/python-stathat
Author: Matt Robenolt
Author-email: matt@ydekproductions.com
License: UNKNOWN
Platform: UNKNOWN
Classifier: Development Status :: 4 - Beta
Classifier: Intended Audience :: Developers
Classifier: License :: OSI Approved :: GNU General Public License (GPL)
Classifier: Operating System :: OS Independent
Classifier: Topic :: Software Development
